./.gitignore
./LICENSE
./MANIFEST.in
./PKG-INFO
./README.md
./__init__.py
./cli.py
./config.py
./history.py
./main.py
./pyproject.toml
./tests/__init__.py
./tests/test_cli.py
neecli-0.3.0.dist-info/METADATA
neecli-0.3.0.dist-info/WHEEL
neecli-0.3.0.dist-info/entry_points.txt
neecli-0.3.0.dist-info/licenses/LICENSE
neecli-0.3.0.dist-info/RECORD
