Metadata-Version: 2.4
Name: neecli
Version: 0.3.0
Summary: A CLI to chat with LLMs (Groq/OpenAI etc.)
Author: Neeraj
License-File: LICENSE
Keywords: ai,chat,cli,groq,llm,openai
Classifier: Development Status :: 4 - Beta
Classifier: Intended Audience :: Developers
Classifier: Programming Language :: Python :: 3
Classifier: Programming Language :: Python :: 3.8
Classifier: Programming Language :: Python :: 3.9
Classifier: Programming Language :: Python :: 3.10
Classifier: Programming Language :: Python :: 3.11
Classifier: Programming Language :: Python :: 3.12
Classifier: Topic :: Communications :: Chat
Classifier: Topic :: Scientific/Engineering :: Artificial Intelligence
Requires-Python: >=3.8
Requires-Dist: click>=8.0
Requires-Dist: openai>=1.0.0
Requires-Dist: python-dotenv>=1.0.0
